MANIFEST.in
README.rst
setup.cfg
setup.py
aocutils/__init__.py
aocutils/collections.py
aocutils/common.py
aocutils/exceptions.py
aocutils/fixes.py
aocutils/iteration.py
aocutils/math_.py
aocutils/memory.py
aocutils/mesh.py
aocutils/pretty_print.py
aocutils/primitives.py
aocutils/random.py
aocutils/tolerance.py
aocutils/topology.py
aocutils/types.py
aocutils.egg-info/PKG-INFO
aocutils.egg-info/SOURCES.txt
aocutils.egg-info/dependency_links.txt
aocutils.egg-info/requires.txt
aocutils.egg-info/top_level.txt
aocutils/analyze/__init__.py
aocutils/analyze/bounds.py
aocutils/analyze/distance.py
aocutils/analyze/global_.py
aocutils/analyze/inclusion.py
aocutils/brep/__init__.py
aocutils/brep/base.py
aocutils/brep/compound_make.py
aocutils/brep/edge.py
aocutils/brep/edge_make.py
aocutils/brep/face.py
aocutils/brep/face_make.py
aocutils/brep/shell.py
aocutils/brep/shell_make.py
aocutils/brep/solid.py
aocutils/brep/solid_make.py
aocutils/brep/vertex.py
aocutils/brep/vertex_make.py
aocutils/brep/wire.py
aocutils/brep/wire_make.py
aocutils/display/__init__.py
aocutils/display/backends.py
aocutils/display/color.py
aocutils/display/defaults.py
aocutils/display/display.py
aocutils/display/safe_yield.py
aocutils/display/texture.py
aocutils/display/topology.py
aocutils/geom/__init__.py
aocutils/geom/_three_d.py
aocutils/geom/curve.py
aocutils/geom/plane.py
aocutils/geom/point.py
aocutils/geom/surface.py
aocutils/geom/vector.py
aocutils/operations/__init__.py
aocutils/operations/boolean.py
aocutils/operations/evolved.py
aocutils/operations/extrude.py
aocutils/operations/geom_split.py
aocutils/operations/interpolate.py
aocutils/operations/intersect.py
aocutils/operations/loft.py
aocutils/operations/offset.py
aocutils/operations/pipe.py
aocutils/operations/project.py
aocutils/operations/section.py
aocutils/operations/sew.py
aocutils/operations/transform.py
aocutils/operations/trim.py