Metadata-Version: 1.1
Name: aocutils
Version: 0.3.0
Summary: High level API for PythonOCC 
Home-page: https://github.com/floatingpointstack/aoc-utils
Author: Guillaume Florent, Adam Lange, Jelle Feringa, Thomas Paviot
Author-email: florentsailing@gmail.com
License: GPL v3
Download-URL: https://github.com/floatingpointstack/aoc-utils/releases/tag/0.3.0
Keywords: OpenCASCADE pythonocc CAD
Platform: UNKNOWN
Classifier: Development Status :: 3 - Alpha
Classifier: Intended Audience :: Developers
Classifier: Topic :: Software Development
Classifier: License :: OSI Approved :: GNU General Public License v3 (GPLv3)
Classifier: Programming Language :: Python :: 2
Classifier: Programming Language :: Python :: 2.7
Classifier: Programming Language :: Python :: 3
Classifier: Programming Language :: Python :: 3.2
Classifier: Programming Language :: Python :: 3.3
Classifier: Programming Language :: Python :: 3.4
